wswebcam/__init__.py
wswebcam/__main__.py
wswebcam/client.py
wswebcam/device.py
wswebcam/protocol.py
wswebcam/server.py
wswebcam-1.1.0.dist-info/LICENSE
wswebcam-1.1.0.dist-info/METADATA
wswebcam-1.1.0.dist-info/WHEEL
wswebcam-1.1.0.dist-info/entry_points.txt
wswebcam-1.1.0.dist-info/top_level.txt
wswebcam-1.1.0.dist-info/RECORD
