Metadata-Version: 2.1
Name: wswebcam
Version: 1.1.0
Summary: Access any serial device in your lan
Author-email: Henrycke Bozza Schenberk <oschenberk@gmail.com>
License: MIT License
Project-URL: Homepage, https://github.com/HenryckeBSchenberk/wswebcam
Keywords: webcam,opencv,streaming,websocket,localhost,image
Classifier: License :: OSI Approved :: MIT License
Classifier: Programming Language :: Python
Classifier: Programming Language :: Python :: 3
Requires-Python: >=3.9
License-File: LICENSE
Requires-Dist: opencv-contrib-python (>=4.6)
Requires-Dist: websockets (>=10.3)
Provides-Extra: dev
Requires-Dist: black ; extra == 'dev'
Requires-Dist: bumpver ; extra == 'dev'
Requires-Dist: isort ; extra == 'dev'
Requires-Dist: pip-tools ; extra == 'dev'
Requires-Dist: unittest ; extra == 'dev'
